kubeler/__init__.py
kubeler/main.py
kubeler/scripts/__init__.py
kubeler/scripts/installer.py
kubeler/scripts/watchdog.py
kubeler/scripts/models/__init__.py
kubeler/scripts/models/kubeler.py
kubeler/scripts/models/kubernetes.py
kubeler-0.1.4.dist-info/LICENSE
kubeler-0.1.4.dist-info/METADATA
kubeler-0.1.4.dist-info/WHEEL
kubeler-0.1.4.dist-info/entry_points.txt
kubeler-0.1.4.dist-info/top_level.txt
kubeler-0.1.4.dist-info/RECORD
