Metadata-Version: 2.2
Name: kubeler
Version: 0.1.4
Summary: A dead simple Kubernetes Resources installer
Home-page: https://github.com/glendmaatita/kubeler
Author: Glend Maatita
Author-email: me@glendmaatita.com
Classifier: Programming Language :: Python :: 3
Classifier: License :: OSI Approved :: MIT License
Classifier: Operating System :: OS Independent
Requires-Python: >=3.12
License-File: LICENSE
Requires-Dist: jinja2>=3.1.5
Requires-Dist: kubernetes>=32.0.0
Requires-Dist: pydantic>=2.10.6
Requires-Dist: python-dotenv>=1.0.1
Requires-Dist: watchdog>=6.0.0
Dynamic: author
Dynamic: author-email
Dynamic: classifier
Dynamic: description
Dynamic: description-content-type
Dynamic: home-page
Dynamic: requires-dist
Dynamic: requires-python
Dynamic: summary
